epy/__init__.py
epy/clear.py
epy/ftdemo.cp38-win_amd64.pyd
epyfund-0.0.1.2022.304.21.dist-info/LICENSE
epyfund-0.0.1.2022.304.21.dist-info/METADATA
epyfund-0.0.1.2022.304.21.dist-info/WHEEL
epyfund-0.0.1.2022.304.21.dist-info/top_level.txt
epyfund-0.0.1.2022.304.21.dist-info/RECORD
