Metadata-Version: 2.1
Name: epyfund
Version: 0.0.1.2022.304.21
Summary: A framework for developing quant trading systems.
Home-page: https://www.EPY.fund
Author: EPY team
Author-email: EPY@EPY.fund
License: MIT
Keywords: quant quantitative investment trading algotrading
Platform: UNKNOWN
Classifier: Operating System :: Microsoft :: Windows :: Windows 10
Classifier: Operating System :: POSIX :: Linux
Classifier: Programming Language :: Python :: 3.8
Classifier: Topic :: Office/Business :: Financial :: Investment
Classifier: Programming Language :: Python :: Implementation :: CPython
Classifier: License :: OSI Approved :: MIT License
Classifier: Natural Language :: Chinese (Simplified)
Requires-Python: >=3.8
License-File: LICENSE
